plain/cache/CHANGELOG.md
plain/cache/README.md
plain/cache/__init__.py
plain/cache/admin.py
plain/cache/chores.py
plain/cache/cli.py
plain/cache/config.py
plain/cache/core.py
plain/cache/models.py
plain/cache/migrations/0001_initial.py
plain/cache/migrations/__init__.py
plain_cache-0.25.0.dist-info/METADATA
plain_cache-0.25.0.dist-info/WHEEL
plain_cache-0.25.0.dist-info/licenses/LICENSE
plain_cache-0.25.0.dist-info/RECORD
