Metadata-Version: 2.4
Name: plain.cache
Version: 0.25.0
Summary: A simple database-backed cache for storing JSON-serializable values with optional expiration.
Author-email: Dave Gaeddert <dave.gaeddert@dropseed.dev>
License-Expression: BSD-3-Clause
License-File: LICENSE
Requires-Python: >=3.13
Requires-Dist: plain<1.0.0
